setup.py
objtrack/__init__.py
objtrack/models.py
objtrack.egg-info/PKG-INFO
objtrack.egg-info/SOURCES.txt
objtrack.egg-info/dependency_links.txt
objtrack.egg-info/top_level.txt
objtrack/templatetags/__init__.py
objtrack/templatetags/tracking.py