Metadata-Version: 1.0
Name: objtrack
Version: 0.2
Summary: Django Object View Tracking
Home-page: http://github.com/dcramer/objtrack/
Author: David Cramer
Author-email: dcramer@gmail.com
License: UNKNOWN
Platform: UNKNOWN
